juriscraper/AbstractSite.py
juriscraper/ClusterSite.py
juriscraper/DeferringList.py
juriscraper/OpinionSite.py
juriscraper/OpinionSiteLinear.py
juriscraper/OpinionSiteLinearWebDriven.py
juriscraper/OpinionSiteWebDriven.py
juriscraper/OralArgumentSite.py
juriscraper/OralArgumentSiteLinear.py
juriscraper/OralArgumentSiteLinearWebDriven.py
juriscraper/WebDriven.py
juriscraper/__init__.py
juriscraper/abstract_parser.py
juriscraper/pacerdocket.py
juriscraper/fdsys/FDSysSite.py
juriscraper/fdsys/__init__.py
juriscraper/fdsys/scrape_court_names.py
juriscraper/fdsys/utils/__init__.py
juriscraper/fdsys/utils/get_metadata.py
juriscraper/fdsys/utils/get_xpath_results.py
juriscraper/lasc/__init__.py
juriscraper/lasc/fetch.py
juriscraper/lasc/http.py
juriscraper/lib/__init__.py
juriscraper/lib/auth_utils.py
juriscraper/lib/cookie_utils.py
juriscraper/lib/date_utils.py
juriscraper/lib/diff_tools.py
juriscraper/lib/exceptions.py
juriscraper/lib/html_utils.py
juriscraper/lib/importer.py
juriscraper/lib/judge_parsers.py
juriscraper/lib/log_tools.py
juriscraper/lib/microservices_utils.py
juriscraper/lib/models.py
juriscraper/lib/network_utils.py
juriscraper/lib/string_utils.py
juriscraper/lib/test_utils.py
juriscraper/lib/type_utils.py
juriscraper/lib/utils.py
juriscraper/opinions/__init__.py
juriscraper/opinions/opinion_template.py
juriscraper/opinions/united_states/__init__.py
juriscraper/opinions/united_states/administrative_agency/__init__.py
juriscraper/opinions/united_states/administrative_agency/asbca.py
juriscraper/opinions/united_states/administrative_agency/bia.py
juriscraper/opinions/united_states/administrative_agency/bva.py
juriscraper/opinions/united_states/administrative_agency/mspb_p.py
juriscraper/opinions/united_states/administrative_agency/mspb_u.py
juriscraper/opinions/united_states/administrative_agency/olc.py
juriscraper/opinions/united_states/federal_appellate/__init__.py
juriscraper/opinions/united_states/federal_appellate/ca1.py
juriscraper-2.7.2.dist-info/licenses/LICENSE
juriscraper-2.7.2.dist-info/METADATA
juriscraper-2.7.2.dist-info/WHEEL
juriscraper-2.7.2.dist-info/top_level.txt
juriscraper-2.7.2.dist-info/RECORD
