Metadata-Version: 2.4
Name: juriscraper
Version: 2.7.2
Summary: An API to scrape American court websites for metadata.
Author-email: Free Law Project <info@free.law>
License-Expression: BSD-2-Clause
Project-URL: Repository, https://github.com/freelawproject/juriscraper
Keywords: scraping,legal,pacer
Classifier: Development Status :: 5 - Production/Stable
Classifier: Intended Audience :: Developers
Classifier: Natural Language :: English
Classifier: Operating System :: OS Independent
Classifier: Programming Language :: Python
Classifier: Programming Language :: Python :: 3
Classifier: Programming Language :: Python :: 3.9
Classifier: Programming Language :: Python :: 3.10
Classifier: Programming Language :: Python :: 3.11
Classifier: Programming Language :: Python :: 3.12
Classifier: Programming Language :: Python :: 3.13
Classifier: Programming Language :: Python :: Implementation :: CPython
Classifier: Programming Language :: Python :: Implementation :: PyPy
Classifier: Topic :: Software Development :: Libraries :: Python Modules
Requires-Python: >=3.9
License-File: LICENSE
Requires-Dist: certifi>=2017.4.17
Requires-Dist: chardet>=3.0.2
Requires-Dist: charset-normalizer>=3.1.0
Requires-Dist: cssselect
Requires-Dist: dateparser>=1.2.0
Requires-Dist: feedparser>=6.0.11
Requires-Dist: geonamescache>=2.0.0
Requires-Dist: html5lib
Requires-Dist: lxml>=5.2
Requires-Dist: nh3
Requires-Dist: python-dateutil>=2.8.2
Requires-Dist: requests>=2.20.0
Requires-Dist: selenium>=4.9.1
Requires-Dist: tldextract
Dynamic: license-file
